pydracogltf/__init__.py
pydracogltf/gltf_draco_decoder.py
pydracogltf/gltf_draco_encoder.py
pydracogltf/libs/libextern_draco.dylib
pydracogltf-0.0.4.dist-info/LICENSE
pydracogltf-0.0.4.dist-info/METADATA
pydracogltf-0.0.4.dist-info/WHEEL
pydracogltf-0.0.4.dist-info/top_level.txt
pydracogltf-0.0.4.dist-info/RECORD
